Workbook

Sheet BWA Bergmann
A1: BWA Kurzreport — Steuerberatung Bergmann GmbH — FY 2025
A3: Position | B3: Jan | C3: Feb | D3: Mrz | E3: Apr | F3: Mai | G3: Jun | H3: Jul | I3: Aug | J3: Sep | K3: Okt | L3: Nov | M3: Dez | N3: Gesamt
A5: 1. Umsatzerlöse
A6: Honorarumsätze Steuerberatung | B6: 42217 | C6: 41143 | D6: 45842 | E6: 47569 | F6: 44183 | G6: 42834 | H6: 44394 | I6: 43871 | J6: 46196 | K6: 48268 | L6: 50533 | M6: 50789 | N6: 547839
A7: Honorarumsätze Lohn/Gehalt | B7: 15149 | C7: 15549 | D7: 16210 | E7: 16626 | F7: 15709 | G7: 15709 | H7: 16106 | I7: 16286 | J7: 16606 | K7: 17180 | L7: 18916 | M7: 19249 | N7: 199295
A8: Honorarumsätze Jahresabschluss | B8: 15481 | C8: 15420 | D8: 15950 | E8: 17392 | F8: 16455 | G8: 15847 | H8: 16950 | I8: 16174 | J8: 16437 | K8: 17249 | L8: 18540 | M8: 18603 | N8: 200498
A9: Sonstige Erlöse | B9: 3786 | C9: 3799 | D9: 4006 | E9: 4168 | F9: 4096 | G9: 3940 | H9: 4241 | I9: 3937 | J9: 4091 | K9: 4455 | L9: 4625 | M9: 4799 | N9: 49943
A10: Gesamtleistung | B10: 76633 | C10: 75911 | D10: 82008 | E10: 85755 | F10: 80443 | G10: 78330 | H10: 81691 | I10: 80268 | J10: 83330 | K10: 87152 | L10: 92614 | M10: 93440 | N10: 997575
A12: 2. Personalaufwand
A13: Gehälter Fachangestellte | B13: 19924 | C13: 19736 | D13: 21322 | E13: 22296 | F13: 20915 | G13: 20365 | H13: 21239 | I13: 20869 | J13: 21665 | K13: 22659 | L13: 24079 | M13: 24294 | N13: 259363
A14: Gehälter Berufsträger | B14: 13947 | C14: 13815 | D14: 14925 | E14: 15607 | F14: 14640 | G14: 14255 | H14: 14867 | I14: 14608 | J14: 15165 | K14: 15861 | L14: 16855 | M14: 17005 | N14: 181550
A15: Sozialabgaben & Nebenkosten | B15: 5978 | C15: 5922 | D15: 6397 | E15: 6689 | F15: 6275 | G15: 6111 | H15: 6373 | I15: 6262 | J15: 6501 | K15: 6799 | L15: 7225 | M15: 7289 | N15: 77821
A16: Personalaufwand gesamt | B16: 39849 | C16: 39473 | D16: 42644 | E16: 44592 | F16: 41830 | G16: 40731 | H16: 42479 | I16: 41739 | J16: 43331 | K16: 45319 | L16: 48159 | M16: 48588 | N16: 518734
A17: in % der Gesamtleistung | B17: =B16/B10 -> 0.51999791 | C17: =C16/C10 -> 0.51999052 | D17: =D16/D10 -> 0.51999805 | E17: =E16/E10 -> 0.519993 | F17: =F16/F10 -> 0.51999552 | G17: =G16/G10 -> 0.51999234 | H17: =H16/H10 -> 0.51999608 | I17: =I16/I10 -> 0.51999552 | ... N17: =N16/N10 -> 0.51999499
A18: € verdient pro € spend in Personalkosten | B18: =B10/B16 -> 1.9230846 | C18: =C10/C16 -> 1.923112 | D18: =D10/D16 -> 1.9230841 | E18: =E10/E16 -> 1.9231028 | F18: =F10/F16 -> 1.9230935 | G18: =G10/G16 -> 1.9231053 | H18: =H10/H16 -> 1.9230914 | I18: =I10/I16 -> 1.9230935 | ... N18: =N10/N16 -> 1.9230955 | O18: =N16 * 'BWA Nowak'!N18 -> 1080726 | P18: =O18/N10 - 1 -> 0.083353098
A20: 3. Sachaufwand
A21: Raumkosten | B21: 4829 | C21: 4676 | D21: 4842 | E21: 4687 | F21: 4800 | G21: 4664 | H21: 4747 | I21: 4889 | J21: 4889 | K21: 4901 | L21: 4800 | M21: 4739 | N21: 57463
A22: IT & Software (ohne DATEV) | B22: 2223 | C22: 2261 | D22: 2263 | E22: 2156 | F22: 2156 | G22: 2166 | H22: 2179 | I22: 2147 | J22: 2144 | K22: 2151 | L22: 2250 | M22: 2149 | N22: 26245
A23: DATEV-Kosten | B23: 3906 | C23: 3829 | D23: 3730 | E23: 3824 | F23: 3874 | G23: 3847 | H23: 3855 | I23: 3784 | J23: 3862 | K23: 3773 | L23: 3846 | M23: 3851 | N23: 45981
A24: Versicherungen | B24: 890 | C24: 901 | D24: 921 | E24: 886 | F24: 919 | G24: 924 | H24: 921 | I24: 887 | J24: 875 | K24: 901 | L24: 892 | M24: 906 | N24: 10823
A25: Büromaterial & Porto | B25: 588 | C25: 583 | D25: 616 | E25: 610 | F25: 599 | G25: 588 | H25: 605 | I25: 599 | J25: 606 | K25: 616 | L25: 592 | M25: 583 | N25: 7185
A26: Reisekosten | B26: 396 | C26: 393 | D26: 389 | E26: 395 | F26: 403 | G26: 392 | H26: 405 | I26: 396 | J26: 395 | K26: 403 | L26: 403 | M26: 392 | N26: 4762
A27: Marketing & Akquise | B27: 198 | C27: 202 | D27: 202 | E27: 202 | F27: 202 | G27: 198 | H27: 203 | I27: 203 | J27: 197 | K27: 204 | L27: 200 | M27: 198 | N27: 2409
A28: Rechts- & Beratungskosten | B28: 510 | C28: 493 | D28: 493 | E28: 500 | F28: 486 | G28: 486 | H28: 505 | I28: 513 | J28: 505 | K28: 505 | L28: 490 | M28: 485 | N28: 5971
A29: Übrige Sachkosten | B29: 788 | C29: 783 | D29: 799 | E29: 815 | F29: 778 | G29: 802 | H29: 779 | I29: 809 | J29: 795 | K29: 776 | L29: 793 | M29: 790 | N29: 9507
A30: Sachaufwand gesamt | B30: 14328 | C30: 14121 | D30: 14255 | E30: 14075 | F30: 14217 | G30: 14067 | H30: 14199 | I30: 14227 | J30: 14268 | K30: 14230 | L30: 14266 | M30: 14093 | N30: 170346
A31: in % der Gesamtleistung | B31: =B30/B10 -> 0.18696906 | C31: =C30/C10 -> 0.18602047 | D31: =D30/D10 -> 0.1738245 | E31: =E30/E10 -> 0.16413037 | F31: =F30/F10 -> 0.17673384 | G31: =G30/G10 -> 0.17958637 | H31: =H30/H10 -> 0.17381352 | I31: =I30/I10 -> 0.17724373 | ... N31: =N30/N10 -> 0.17076009 | O31: =M30/'Kanzlei-Profil'!B6 -> 880.8125
A33: EBITDA | B33: 22456 | C33: 22317 | D33: 25109 | E33: 27088 | F33: 24396 | G33: 23532 | H33: 25013 | I33: 24302 | J33: 25731 | K33: 27603 | L33: 30189 | M33: 30759 | N33: 308495
A34: EBITDA-Marge | B34: 0.29303303 | C34: 0.29398901 | D34: 0.30617745 | E34: 0.31587663 | F34: 0.30327064 | G34: 0.30042129 | H34: 0.3061904 | I34: 0.30276075 | J34: 0.30878435 | K34: 0.31672251 | L34: 0.32596584 | M34: 0.3291845 | N34: 0.30924492
A36: Abschreibungen | B36: 1164 | C36: 1169 | D36: 1233 | E36: 1184 | F36: 1169 | G36: 1185 | H36: 1172 | I36: 1217 | J36: 1170 | K36: 1228 | L36: 1200 | M36: 1206 | N36: 14297
A37: EBIT | B37: 21292 | C37: 21148 | D37: 23876 | E37: 25904 | F37: 23227 | G37: 22347 | H37: 23841 | I37: 23085 | J37: 24561 | K37: 26375 | L37: 28989 | M37: 29553 | N37: 294198
A38: EBIT-Marge | B38: 0.27784375 | C38: 0.2785894 | D38: 0.29114233 | E38: 0.30206985 | F38: 0.28873861 | G38: 0.28529299 | H38: 0.29184365 | I38: 0.28759904 | J38: 0.29474379 | K38: 0.30263218 | L38: 0.31300883 | M38: 0.31627783 | N38: 0.29491316
A40: Zinsen & ähnliche Aufwendungen | B40: 151 | C40: 152 | D40: 148 | E40: 151 | F40: 146 | G40: 150 | H40: 150 | I40: 148 | J40: 149 | K40: 152 | L40: 154 | M40: 151 | N40: 1802
A41: EBT | B41: 21141 | C41: 20996 | D41: 23728 | E41: 25753 | F41: 23081 | G41: 22197 | H41: 23691 | I41: 22937 | J41: 24412 | K41: 26223 | L41: 28835 | M41: 29402 | N41: 292396

Sheet BWA Fiedler
A1: BWA Kurzreport — Kanzlei Fiedler & Partner mbB — FY 2025
A3: Position | B3: Jan | C3: Feb | D3: Mrz | E3: Apr | F3: Mai | G3: Jun | H3: Jul | I3: Aug | J3: Sep | K3: Okt | L3: Nov | M3: Dez | N3: Gesamt
A5: 1. Umsatzerlöse
A6: Honorarumsätze Steuerberatung | B6: 56721 | C6: 54117 | D6: 61166 | E6: 61059 | F6: 60157 | G6: 56172 | H6: 56629 | I6: 57088 | J6: 59099 | K6: 62210 | L6: 66378 | M6: 67109 | N6: 717905
A7: Honorarumsätze Lohn/Gehalt | B7: 20374 | C7: 19879 | D7: 21370 | E7: 22026 | F7: 21323 | G7: 20373 | H7: 21281 | I7: 20424 | J7: 21602 | K7: 23445 | L7: 24302 | M7: 24732 | N7: 261131
A8: Honorarumsätze Jahresabschluss | B8: 21300 | C8: 19312 | D8: 21407 | E8: 22140 | F8: 21982 | G8: 20259 | H8: 21650 | I8: 20635 | J8: 21837 | K8: 23169 | L8: 23263 | M8: 23761 | N8: 260715
A9: Sonstige Erlöse | B9: 5305 | C9: 4949 | D9: 5354 | E9: 5687 | F9: 5371 | G9: 5235 | H9: 5421 | I9: 5102 | J9: 5360 | K9: 5888 | L9: 5754 | M9: 5919 | N9: 65345
A10: Gesamtleistung | B10: 103700 | C10: 98257 | D10: 109297 | E10: 110912 | F10: 108833 | G10: 102039 | H10: 104981 | I10: 103249 | J10: 107898 | K10: 114712 | L10: 119697 | M10: 121521 | N10: 1305096
A12: 2. Personalaufwand
A13: Gehälter Fachangestellte | B13: 32665 | C13: 30950 | D13: 34428 | E13: 34937 | F13: 34282 | G13: 32142 | H13: 33069 | I13: 32523 | J13: 33987 | K13: 36134 | L13: 37704 | M13: 38279 | N13: 411100
A14: Gehälter Berufsträger | B14: 22865 | C14: 21665 | D14: 24099 | E14: 24455 | F14: 23997 | G14: 22499 | H14: 23148 | I14: 22766 | J14: 23791 | K14: 25293 | L14: 26393 | M14: 26795 | N14: 287766
A15: Sozialabgaben & Nebenkosten | B15: 9801 | C15: 9286 | D15: 10330 | E15: 10482 | F15: 10285 | G15: 9643 | H15: 9921 | I15: 9757 | J15: 10197 | K15: 10841 | L15: 11312 | M15: 11484 | N15: 123339
A16: Personalaufwand gesamt | B16: 65331 | C16: 61901 | D16: 68857 | E16: 69874 | F16: 68564 | G16: 64284 | H16: 66138 | I16: 65046 | J16: 67975 | K16: 72268 | L16: 75409 | M16: 76558 | N16: 822205
A17: in % der Gesamtleistung | B17: =B16/B10 -> 0.63 | C17: =C16/C10 -> 0.62999074 | D17: =D16/D10 -> 0.62999899 | E17: =E16/E10 -> 0.62999495 | F17: =F16/F10 -> 0.62999274 | G17: =G16/G10 -> 0.62999441 | H17: =H16/H10 -> 0.62999971 | I17: =I16/I10 -> 0.62999157 | ... N17: =N16/N10 -> 0.6299958
A18: € verdient pro € spend in Personalkosten | B18: =B10/B16 -> 1.5873016 | C18: =C10/C16 -> 1.5873249 | D18: =D10/D16 -> 1.5873041 | E18: =E10/E16 -> 1.5873143 | F18: =F10/F16 -> 1.5873199 | G18: =G10/G16 -> 1.5873157 | H18: =H10/H16 -> 1.5873023 | I18: =I10/I16 -> 1.5873228 | ... N18: =N10/N16 -> 1.5873122 | O18: =N16*'BWA Nowak'!N18 -> 1712974.8 | P18: =O18/N10 - 1 -> 0.31252785
A20: 3. Sachaufwand
A21: Raumkosten | B21: 7225 | C21: 7064 | D21: 7339 | E21: 7227 | F21: 7317 | G21: 7144 | H21: 7264 | I21: 7065 | J21: 7250 | K21: 7211 | L21: 7345 | M21: 7321 | N21: 86772
A22: IT & Software (ohne DATEV) | B22: 1816 | C22: 1761 | D22: 1753 | E22: 1825 | F22: 1779 | G22: 1802 | H22: 1846 | I22: 1820 | J22: 1747 | K22: 1793 | L22: 1818 | M22: 1845 | N22: 21605
A23: DATEV-Kosten | B23: 5199 | C23: 5067 | D23: 5127 | E23: 5208 | F23: 5319 | G23: 5088 | H23: 5220 | I23: 5197 | J23: 5354 | K23: 5202 | L23: 5328 | M23: 5231 | N23: 62540
A24: Versicherungen | B24: 1417 | C24: 1428 | D24: 1363 | E24: 1411 | F24: 1391 | G24: 1366 | H24: 1362 | I24: 1380 | J24: 1433 | K24: 1380 | L24: 1389 | M24: 1392 | N24: 16712
A25: Büromaterial & Porto | B25: 1083 | C25: 1131 | D25: 1100 | E25: 1109 | F25: 1117 | G25: 1116 | H25: 1067 | I25: 1107 | J25: 1107 | K25: 1115 | L25: 1102 | M25: 1095 | N25: 13249
A26: Reisekosten | B26: 798 | C26: 809 | D26: 796 | E26: 801 | F26: 797 | G26: 800 | H26: 787 | I26: 782 | J26: 816 | K26: 808 | L26: 808 | M26: 789 | N26: 9591
A27: Marketing & Akquise | B27: 97 | C27: 100 | D27: 100 | E27: 102 | F27: 99 | G27: 102 | H27: 100 | I27: 97 | J27: 100 | K27: 98 | L27: 98 | M27: 101 | N27: 1194
A28: Rechts- & Beratungskosten | B28: 717 | C28: 696 | D28: 690 | E28: 691 | F28: 716 | G28: 697 | H28: 682 | I28: 719 | J28: 695 | K28: 711 | L28: 717 | M28: 718 | N28: 8449
A29: Übrige Sachkosten | B29: 1483 | C29: 1473 | D29: 1490 | E29: 1534 | F29: 1506 | G29: 1455 | H29: 1504 | I29: 1530 | J29: 1513 | K29: 1472 | L29: 1521 | M29: 1534 | N29: 18015
A30: Sachaufwand gesamt | B30: 19835 | C30: 19529 | D30: 19758 | E30: 19908 | F30: 20041 | G30: 19570 | H30: 19832 | I30: 19697 | J30: 20015 | K30: 19790 | L30: 20126 | M30: 20026 | N30: 238127
A31: in % der Gesamtleistung | B31: =B30/B10 -> 0.1912729 | C31: =C30/C10 -> 0.19875429 | D31: =D30/D10 -> 0.18077349 | E31: =E30/E10 -> 0.17949365 | F31: =F30/F10 -> 0.18414451 | G31: =G30/G10 -> 0.19178941 | H31: =H30/H10 -> 0.18891037 | I31: =I30/I10 -> 0.19077182 | ... N31: =N30/N10 -> 0.18245937 | O31: =M30/'Kanzlei-Profil'!C6 -> 953.61905
A33: EBITDA | B33: 18534 | C33: 16827 | D33: 20682 | E33: 21130 | F33: 20228 | G33: 18185 | H33: 19011 | I33: 18506 | J33: 19908 | K33: 22654 | L33: 24162 | M33: 24937 | N33: 244764
A34: EBITDA-Marge | B34: 0.1787271 | C34: 0.17125497 | D34: 0.18922752 | E34: 0.1905114 | F34: 0.18586274 | G34: 0.17821617 | H34: 0.18108991 | I34: 0.1792366 | J34: 0.18450759 | K34: 0.19748588 | L34: 0.2018597 | M34: 0.20520733 | N34: 0.18754482
A36: Abschreibungen | B36: 1942 | C36: 1953 | D36: 1967 | E36: 2030 | F36: 1991 | G36: 2049 | H36: 1984 | I36: 2021 | J36: 2030 | K36: 1969 | L36: 1998 | M36: 1951 | N36: 23885
A37: EBIT | B37: 16592 | C37: 14874 | D37: 18715 | E37: 19100 | F37: 18237 | G37: 16136 | H37: 17027 | I37: 16485 | J37: 17878 | K37: 20685 | L37: 22164 | M37: 22986 | N37: 220879
A38: EBIT-Marge | B38: 0.16 | C38: 0.15137853 | D38: 0.17123068 | E38: 0.1722086 | F38: 0.16756866 | G38: 0.15813561 | H38: 0.16219125 | I38: 0.15966256 | J38: 0.16569353 | K38: 0.18032115 | L38: 0.18516755 | M38: 0.18915249 | N38: 0.16924349
A40: Zinsen & ähnliche Aufwendungen | B40: 444 | C40: 440 | D40: 447 | E40: 443 | F40: 451 | G40: 456 | H40: 455 | I40: 445 | J40: 438 | K40: 439 | L40: 455 | M40: 439 | N40: 5352
A41: EBT | B41: 16148 | C41: 14434 | D41: 18268 | E41: 18657 | F41: 17786 | G41: 15680 | H41: 16572 | I41: 16040 | J41: 17440 | K41: 20246 | L41: 21709 | M41: 22547 | N41: 215527

Sheet BWA Nowak
A1: BWA Kurzreport — STB Nowak GmbH — FY 2025
A3: Position | B3: Jan | C3: Feb | D3: Mrz | E3: Apr | F3: Mai | G3: Jun | H3: Jul | I3: Aug | J3: Sep | K3: Okt | L3: Nov | M3: Dez | N3: Gesamt
A5: 1. Umsatzerlöse
A6: Honorarumsätze Steuerberatung | B6: 20957 | C6: 19557 | D6: 23432 | E6: 24827 | F6: 22463 | G6: 21890 | H6: 25299 | I6: 23353 | J6: 25732 | K6: 29029 | L6: 29618 | M6: 31354 | N6: 297511
A7: Honorarumsätze Lohn/Gehalt | B7: 7498 | C7: 7340 | D7: 8167 | E7: 8912 | F7: 8263 | G7: 8051 | H7: 8970 | I7: 8773 | J7: 9558 | K7: 10342 | L7: 11060 | M7: 11761 | N7: 108695
A8: Honorarumsätze Jahresabschluss | B8: 7405 | C8: 7073 | D8: 8156 | E8: 8895 | F8: 8248 | G8: 8120 | H8: 9094 | I8: 8681 | J8: 9479 | K8: 10112 | L8: 10799 | M8: 11540 | N8: 107602
A9: Sonstige Erlöse | B9: 1869 | C9: 1836 | D9: 2086 | E9: 2211 | F9: 2109 | G9: 1956 | H9: 2261 | I9: 2109 | J9: 2362 | K9: 2623 | L9: 2773 | M9: 2960 | N9: 27155
A10: Gesamtleistung | B10: 37729 | C10: 35806 | D10: 41841 | E10: 44845 | F10: 41083 | G10: 40017 | H10: 45624 | I10: 42916 | J10: 47131 | K10: 52106 | L10: 54250 | M10: 57615 | N10: 540963
A12: 2. Personalaufwand
A13: Gehälter Fachangestellte | B13: 9054 | C13: 8593 | D13: 10041 | E13: 10762 | F13: 9859 | G13: 9604 | H13: 10949 | I13: 10299 | J13: 11311 | K13: 12505 | L13: 13020 | M13: 13827 | N13: 129824
A14: Gehälter Berufsträger | B14: 6338 | C14: 6015 | D14: 7029 | E14: 7533 | F14: 6901 | G14: 6722 | H14: 7664 | I14: 7209 | J14: 7917 | K14: 8753 | L14: 9114 | M14: 9679 | N14: 90874
A15: Sozialabgaben & Nebenkosten | B15: 2717 | C15: 2578 | D15: 3013 | E15: 3230 | F15: 2959 | G15: 2882 | H15: 3286 | I15: 3091 | J15: 3394 | K15: 3752 | L15: 3906 | M15: 4149 | N15: 38957
A16: Personalaufwand gesamt | B16: 18109 | C16: 17186 | D16: 20083 | E16: 21525 | F16: 19719 | G16: 19208 | H16: 21899 | I16: 20599 | J16: 22622 | K16: 25010 | L16: 26040 | M16: 27655 | N16: 259655
A17: in % der Gesamtleistung | B17: =B16/B10 -> 0.47997562 | C17: =C16/C10 -> 0.47997542 | D17: =D16/D10 -> 0.47998375 | E17: =E16/E10 -> 0.47998662 | F17: =F16/F10 -> 0.47997955 | G17: =G16/G10 -> 0.479996 | H17: =H16/H10 -> 0.4799886 | I17: =I16/I10 -> 0.47998416 | ... N17: =N16/N10 -> 0.47998662
A18: € verdient pro € spend in Personalkosten | B18: =B10/B16 -> 2.0834392 | C18: =C10/C16 -> 2.08344 | D18: =D10/D16 -> 2.0834039 | E18: =E10/E16 -> 2.0833914 | F18: =F10/F16 -> 2.0834221 | G18: =G10/G16 -> 2.0833507 | H18: =H10/H16 -> 2.0833828 | I18: =I10/I16 -> 2.0834021 | ... N18: =N10/N16 -> 2.0833914
A20: 3. Sachaufwand
A21: Raumkosten | B21: 2221 | C21: 2160 | D21: 2184 | E21: 2145 | F21: 2245 | G21: 2209 | H21: 2219 | I21: 2215 | J21: 2219 | K21: 2212 | L21: 2208 | M21: 2160 | N21: 26397
A22: IT & Software (ohne DATEV) | B22: 1755 | C22: 1761 | D22: 1773 | E22: 1848 | F22: 1843 | G22: 1830 | H22: 1767 | I22: 1851 | J22: 1804 | K22: 1813 | L22: 1824 | M22: 1850 | N22: 21719
A23: DATEV-Kosten | B23: 2104 | C23: 2067 | D23: 2059 | E23: 2079 | F23: 2073 | G23: 2155 | H23: 2144 | I23: 2140 | J23: 2114 | K23: 2077 | L23: 2142 | M23: 2101 | N23: 25255
A24: Versicherungen | B24: 503 | C24: 498 | D24: 497 | E24: 492 | F24: 504 | G24: 505 | H24: 512 | I24: 485 | J24: 505 | K24: 491 | L24: 508 | M24: 508 | N24: 6008
A25: Büromaterial & Porto | B25: 304 | C25: 307 | D25: 301 | E25: 299 | F25: 303 | G25: 291 | H25: 303 | I25: 293 | J25: 297 | K25: 306 | L25: 299 | M25: 294 | N25: 3597
A26: Reisekosten | B26: 201 | C26: 201 | D26: 205 | E26: 195 | F26: 204 | G26: 199 | H26: 202 | I26: 204 | J26: 197 | K26: 194 | L26: 198 | M26: 197 | N26: 2397
A27: Marketing & Akquise | B27: 582 | C27: 592 | D27: 606 | E27: 608 | F27: 615 | G27: 612 | H27: 594 | I27: 610 | J27: 593 | K27: 593 | L27: 583 | M27: 612 | N27: 7200
A28: Rechts- & Beratungskosten | B28: 300 | C28: 294 | D28: 305 | E28: 307 | F28: 303 | G28: 306 | H28: 306 | I28: 299 | J28: 295 | K28: 302 | L28: 299 | M28: 298 | N28: 3614
A29: Übrige Sachkosten | B29: 398 | C29: 399 | D29: 404 | E29: 401 | F29: 408 | G29: 405 | H29: 396 | I29: 393 | J29: 399 | K29: 411 | L29: 396 | M29: 410 | N29: 4820
A30: Sachaufwand gesamt | B30: 8368 | C30: 8279 | D30: 8334 | E30: 8374 | F30: 8498 | G30: 8512 | H30: 8443 | I30: 8490 | J30: 8423 | K30: 8399 | L30: 8457 | M30: 8430 | N30: 101007
A31: in % der Gesamtleistung | B31: =B30/B10 -> 0.22179226 | C31: =C30/C10 -> 0.23121823 | D31: =D30/D10 -> 0.19918262 | E31: =E30/E10 -> 0.18673208 | F31: =F30/F10 -> 0.20684955 | G31: =G30/G10 -> 0.2127096 | H31: =H30/H10 -> 0.18505611 | I31: =I30/I10 -> 0.19782832 | ... N31: =N30/N10 -> 0.18671702 | O31: =M30/'Kanzlei-Profil'!D6 -> 1053.75
A33: EBITDA | B33: 11252 | C33: 10341 | D33: 13424 | E33: 14946 | F33: 12866 | G33: 12297 | H33: 15282 | I33: 13827 | J33: 16086 | K33: 18697 | L33: 19753 | M33: 21530 | N33: 180301
A34: EBITDA-Marge | B34: 0.29823213 | C34: 0.28880635 | D34: 0.32083363 | E34: 0.3332813 | F34: 0.3131709 | G34: 0.3072944 | H34: 0.33495529 | I34: 0.32218753 | J34: 0.34130402 | K34: 0.35882624 | L34: 0.3641106 | M34: 0.37368741 | N34: 0.33329636
A36: Abschreibungen | B36: 782 | C36: 817 | D36: 781 | E36: 789 | F36: 784 | G36: 788 | H36: 815 | I36: 787 | J36: 793 | K36: 791 | L36: 818 | M36: 796 | N36: 9541
A37: EBIT | B37: 10470 | C37: 9524 | D37: 12643 | E37: 14157 | F37: 12082 | G37: 11509 | H37: 14467 | I37: 13040 | J37: 15293 | K37: 17906 | L37: 18935 | M37: 20734 | N37: 170760
A38: EBIT-Marge | B38: 0.27750537 | C38: 0.26598894 | D38: 0.30216773 | E38: 0.31568737 | F38: 0.29408758 | G38: 0.28760277 | H38: 0.31709188 | I38: 0.30384938 | J38: 0.32447858 | K38: 0.34364565 | L38: 0.34903226 | M38: 0.35987156 | N38: 0.3156593
A40: Zinsen & ähnliche Aufwendungen | B40: 51 | C40: 49 | D40: 49 | E40: 48 | F40: 50 | G40: 50 | H40: 50 | I40: 50 | J40: 49 | K40: 49 | L40: 50 | M40: 48 | N40: 593
A41: EBT | B41: 10419 | C41: 9475 | D41: 12594 | E41: 14109 | F41: 12032 | G41: 11459 | H41: 14417 | I41: 12990 | J41: 15244 | K41: 17857 | L41: 18885 | M41: 20686 | N41: 170167

Sheet Kanzlei-Profil
A1: Kanzlei-Profil — Operative Kennzahlen
A3: Kennzahl | B3: Bergmann (Stuttgart) | C3: Fiedler (Dortmund) | D3: Nowak (Leipzig)
A4: Gründungsjahr | B4: 2001 | C4: 1994 | D4: 2018
A5: Berufsträger (Partner) | B5: 2 | C5: 3 | D5: 1
A6: Fachkräfte (FTE) | B6: 16 | C6: 21 | D6: 8
A7: Mitarbeiter gesamt | B7: 18 | C7: 24 | D7: 9
A8: Mandate aktiv | B8: 420 | C8: 580 | D8: 180
A9: Ø Honorar je Mandat (EUR/Jahr) | B9: ~2.400 | C9: ~2.200 | D9: ~3.200
A11: Mandatsmix: Fibu/Laufende Beratung | B11: 55% | C11: 50% | D11: 45%
A12: Mandatsmix: Lohn & Gehalt | B12: 20% | C12: 25% | D12: 15%
A13: Mandatsmix: Jahresabschluss/Steuererklärung | B13: 20% | C13: 20% | D13: 25%
A14: Mandatsmix: Sonderberatung/Projekte | B14: 5% | C14: 5% | D14: 15%
A16: DATEV-Module | B16: UO, Kanzlei-Rewe, Lodas, DMS | C16: Kanzlei-Rewe, Lodas, EO comfort | D16: UO, SmartTransfer, Kanzlei-Rewe, LuG, DMS
A17: Digitalisierungsgrad | B17: Mittel | C17: Niedrig | D17: Hoch
A18: Anteil digitale Belege | B18: ~50% | C18: ~15% | D18: ~85%
A19: Cloud-Telefonie | B19: Nein | C19: Nein | D19: Ja
A20: Mandantenportal aktiv | B20: Ja (DATEV UO) | C20: Nein | D20: Ja (DATEV UO + eigenes)
A22: Nachfolgesituation | B22: Partner 62 + 58 J. Nachfolge ungeklärt | C22: Partner 67 + 61 + 54 J. Seniorpartner sucht Exit | D22: Gründer 34 J. Wachstumsorientiert
A23: Fluktuation (letzte 12M) | B23: 2 Abgänge | C23: 5 Abgänge | D23: 0 Abgänge
... A25: Überstundenquote | B25: Moderat | C25: Hoch (Steuersaison) | D25: Niedrig
